sphinx_uml/__init__.py
sphinx_uml/pyreverse/__init__.py
sphinx_uml/pyreverse/cli.py
sphinx_uml/pyreverse/dot_printer.py
sphinx_uml/pyreverse/main.py
sphinx_uml/pyreverse/sphinx_html_proxy.py
sphinx_uml/singleton.py
sphinx_uml/uml_generate_directive.py
sphinx_uml-0.4.0.dist-info/METADATA
sphinx_uml-0.4.0.dist-info/WHEEL
sphinx_uml-0.4.0.dist-info/entry_points.txt
sphinx_uml-0.4.0.dist-info/licenses/AUTHORS.md
sphinx_uml-0.4.0.dist-info/licenses/LICENSE
sphinx_uml-0.4.0.dist-info/RECORD
