Metadata-Version: 2.4
Name: sphinx-uml
Version: 0.4.0
Summary: Build UML diagrams in the documentation.
License: BSD-3
License-File: AUTHORS.md
License-File: LICENSE
Author: Marc-Olivier Buob
Author-email: marc-olivier.buob@nokia-bell-labs.com
Requires-Python: >= 3.9
Classifier: Development Status :: 2 - Pre-Alpha
Classifier: Intended Audience :: Developers
Classifier: License :: OSI Approved :: Python Software Foundation License
Classifier: Natural Language :: English
Classifier: Programming Language :: Python :: 3 :: Only
Classifier: Programming Language :: Python :: 3.9
Classifier: Programming Language :: Python :: 3.10
Classifier: Programming Language :: Python :: 3.11
Classifier: Programming Language :: Python :: 3.12
Classifier: Programming Language :: Python :: 3.13
Classifier: Topic :: Documentation :: Sphinx
Provides-Extra: tests
Requires-Dist: docutils
Requires-Dist: pylint
Requires-Dist: pytest ; extra == "tests"
Requires-Dist: sphinx
Project-URL: Changelog, https://github.com/ibgp2/sphinx-pyreverse/HISTORY.md
Project-URL: Repository, https://github.com/ibgp2/sphinx-pyreverse
